bumms/__init__.py
bumms/__main__.py
bumms/ascii.bumms
bumms/core.py
bumms/knall1.mp3
bumms/knall2.mp3
bumms/knall3.mp3
bumms/txt.bumms
bumms/video.mp4
bumms-1.5.1.dist-info/METADATA
bumms-1.5.1.dist-info/WHEEL
bumms-1.5.1.dist-info/entry_points.txt
bumms-1.5.1.dist-info/top_level.txt
bumms-1.5.1.dist-info/RECORD
